setup.cfg
setup.py
pazudorasolver/__init__.py
pazudorasolver/board.py
pazudorasolver/piece.py
pazudorasolver/solver.py
pazudorasolver.egg-info/PKG-INFO
pazudorasolver.egg-info/SOURCES.txt
pazudorasolver.egg-info/dependency_links.txt
pazudorasolver.egg-info/requires.txt
pazudorasolver.egg-info/top_level.txt
pazudorasolver/heuristics/__init__.py
pazudorasolver/heuristics/greedy_dfs.py
pazudorasolver/heuristics/heuristic.py
pazudorasolver/heuristics/pruned_bfs.py