Metadata-Version: 1.1
Name: pazudorasolver
Version: 0.2.2
Summary: Puzzles and Dragons board solver
Home-page: https://github.com/ethanlu/pazudora-solver
Author: Ethan Fang Lu
Author-email: fang.lu@gmail.com
License: MIT
Download-URL: https://github.com/ethanlu/pazudora-solver/releases
Keywords: pad
Platform: UNKNOWN
Classifier: Development Status :: 4 - Beta
Classifier: License :: OSI Approved :: MIT License
Classifier: Programming Language :: Python
Classifier: Programming Language :: Python :: 3
Classifier: Programming Language :: Python :: 3.4
Classifier: Programming Language :: Python :: 3.5
Classifier: Programming Language :: Python :: 3.6
Classifier: Topic :: Games/Entertainment :: Puzzle Games
